rich_inquirer/__init__.py
rich_inquirer/context.py
rich_inquirer/base/__init__.py
rich_inquirer/base/base_prompt.py
rich_inquirer/base/choice.py
rich_inquirer/prompt/__init__.py
rich_inquirer/prompt/confirm.py
rich_inquirer/prompt/fuzzy.py
rich_inquirer/prompt/select.py
rich_inquirer/prompt/text.py
rich_inquirer-0.1.6.dist-info/licenses/LICENSE
rich_inquirer-0.1.6.dist-info/METADATA
rich_inquirer-0.1.6.dist-info/WHEEL
rich_inquirer-0.1.6.dist-info/top_level.txt
rich_inquirer-0.1.6.dist-info/RECORD
