Metadata-Version: 2.4
Name: rich-inquirer
Version: 0.1.6
Summary: Interactive CLI prompts using Rich and readchar, inspired by python-inquirer
Author-email: Choi Seokgyu <csq1404@gmail.com>
License-Expression: MIT
Project-URL: Homepage, https://github.com/chosey0/rich-inquirer
Project-URL: Repository, https://github.com/chosey0/rich-inquirer
Requires-Python: >=3.8
License-File: LICENSE
Requires-Dist: rich>=13.0.0
Requires-Dist: readchar>=4.0.0
Requires-Dist: rapidfuzz>=3.0.0
Dynamic: license-file
